urban_dictionary_parser_py/__init__.py
urban_dictionary_parser_py/urban_dictionary_parser_py.py
urban_dictionary_parser_py-0.1.dist-info/LICENSE
urban_dictionary_parser_py-0.1.dist-info/METADATA
urban_dictionary_parser_py-0.1.dist-info/WHEEL
urban_dictionary_parser_py-0.1.dist-info/top_level.txt
urban_dictionary_parser_py-0.1.dist-info/RECORD
